<?xml version="1.0" encoding="utf-8"?>
<Dependencies>
  <ProductDependencies>
    <Dependency Name="Microsoft.NETCore.App.Ref" Version="8.0.15" CoherentParentDependency="Microsoft.Dotnet.Sdk.Internal">
      <Uri>https://dev.azure.com/dnceng/internal/_git/dotnet-runtime</Uri>
      <Sha>50c4cb9fc31c47f03eac865d7bc518af173b74b7</Sha>
    </Dependency>
    <Dependency Name="Microsoft.NET.Workload.Emscripten.Current.Manifest-8.0.100" Version="8.0.15" CoherentParentDependency="Microsoft.Dotnet.Sdk.Internal">
      <Uri>https://github.com/dotnet/emsdk</Uri>
      <Sha>6afd7b9f34943078f2e3b747f33350e5fe114269</Sha>
    </Dependency>
    <Dependency Name="Microsoft.NET.Sdk.Android.Manifest-8.0.100" Version="34.0.154">
      <Uri>https://github.com/dotnet/android</Uri>
      <Sha>82d8938cf80f6d5fa6c28529ddfbdb753d805ab4</Sha>
    </Dependency>
    <Dependency Name="Microsoft.NET.Sdk.iOS.Manifest-8.0.100" Version="18.0.8319">
      <Uri>https://github.com/xamarin/xamarin-macios</Uri>
      <Sha>0ee28379dd5e85c830bad0270d064bbcec467647</Sha>
    </Dependency>
    <Dependency Name="Microsoft.NET.Sdk.tvOS.Manifest-8.0.100" Version="18.0.8319">
      <Uri>https://github.com/xamarin/xamarin-macios</Uri>
      <Sha>0ee28379dd5e85c830bad0270d064bbcec467647</Sha>
    </Dependency>
    <Dependency Name="Microsoft.NET.Sdk.MacCatalyst.Manifest-8.0.100" Version="18.0.8319">
      <Uri>https://github.com/xamarin/xamarin-macios</Uri>
      <Sha>0ee28379dd5e85c830bad0270d064bbcec467647</Sha>
    </Dependency>
    <Dependency Name="Microsoft.NET.Sdk.macOS.Manifest-8.0.100" Version="15.0.8319">
      <Uri>https://github.com/xamarin/xamarin-macios</Uri>
      <Sha>0ee28379dd5e85c830bad0270d064bbcec467647</Sha>
    </Dependency>
    <Dependency Name="Microsoft.NET.Sdk.Maui.Manifest-8.0.100" Version="8.0.100">
      <Uri>https://github.com/dotnet/maui</Uri>
      <Sha>f4dbb744f19d479c9dc0582e97ba7753df149638</Sha>
    </Dependency>
    <Dependency Name="Microsoft.Dotnet.Sdk.Internal" Version="8.0.409-servicing.25209.4">
      <Uri>https://dev.azure.com/dnceng/internal/_git/dotnet-installer</Uri>
      <Sha>8ac725554d6697b3fd7c46c4a4b031ef63f29855</Sha>
    </Dependency>
  </ProductDependencies>
  <ToolsetDependencies>
    <Dependency Name="Microsoft.DotNet.Arcade.Sdk" Version="8.0.0-beta.25120.1">
      <Uri>https://github.com/dotnet/arcade</Uri>
      <Sha>4ff4ce248e95ae74b0040de6a6c5939aa63120dc</Sha>
    </Dependency>
  </ToolsetDependencies>
</Dependencies>
