<?xml version="1.0" encoding="utf-8"?>
<Dependencies>
  <ProductDependencies>
    <Dependency Name="Microsoft.NET.Workload.Emscripten.Current.Manifest-11.0.100-preview.6" Version="11.0.100-preview.6.26359.118">
      <Uri>https://github.com/dotnet/dotnet</Uri>
      <Sha>ba53d0ed335bed4ab7bfd01988c8e3953ee5ffbe</Sha>
      <SourceBuild RepoName="emsdk" ManagedOnly="true" />
    </Dependency>
    <Dependency Name="Microsoft.NET.Workload.Mono.Toolchain.Current.Manifest-11.0.100-preview.6" Version="11.0.100-preview.6.26359.118">
      <Uri>https://github.com/dotnet/dotnet</Uri>
      <Sha>ba53d0ed335bed4ab7bfd01988c8e3953ee5ffbe</Sha>
    </Dependency>
    <Dependency Name="Microsoft.NET.Sdk.Android.Manifest-11.0.100-preview.6" Version="37.0.0-preview.6.59">
      <Uri>https://github.com/dotnet/android</Uri>
      <Sha>a2d46b3546d1d445a7164dc239a4ae7e5a8332a0</Sha>
    </Dependency>
    <Dependency Name="Microsoft.NET.Sdk.iOS.Manifest-11.0.100-preview.6" Version="26.5.11720-net11-p6">
      <Uri>https://github.com/dotnet/macios</Uri>
      <Sha>624e2ab62edc07bfa325abb6ff16ec058c7cbcff</Sha>
    </Dependency>
    <Dependency Name="Microsoft.NET.Sdk.tvOS.Manifest-11.0.100-preview.6" Version="26.5.11720-net11-p6">
      <Uri>https://github.com/dotnet/macios</Uri>
      <Sha>624e2ab62edc07bfa325abb6ff16ec058c7cbcff</Sha>
    </Dependency>
    <Dependency Name="Microsoft.NET.Sdk.MacCatalyst.Manifest-11.0.100-preview.6" Version="26.5.11720-net11-p6">
      <Uri>https://github.com/dotnet/macios</Uri>
      <Sha>624e2ab62edc07bfa325abb6ff16ec058c7cbcff</Sha>
    </Dependency>
    <Dependency Name="Microsoft.NET.Sdk.macOS.Manifest-11.0.100-preview.6" Version="26.5.11720-net11-p6">
      <Uri>https://github.com/dotnet/macios</Uri>
      <Sha>624e2ab62edc07bfa325abb6ff16ec058c7cbcff</Sha>
    </Dependency>
    <Dependency Name="Microsoft.NET.Sdk.Maui.Manifest-11.0.100-preview.6" Version="11.0.0-preview.6.26360.8">
      <Uri>https://github.com/dotnet/maui</Uri>
      <Sha>e7264838d83d55430b219a23cc0e5da6e8b04e9a</Sha>
    </Dependency>
  </ProductDependencies>
  <ToolsetDependencies>
    <Dependency Name="Microsoft.DotNet.Arcade.Sdk" Version="11.0.0-beta.26359.118">
      <Uri>https://github.com/dotnet/dotnet</Uri>
      <Sha>ba53d0ed335bed4ab7bfd01988c8e3953ee5ffbe</Sha>
      <SourceBuild RepoName="arcade" ManagedOnly="true" />
    </Dependency>
  </ToolsetDependencies>
</Dependencies>
